[
  {
    "date": "2026-04-24",
    "market_data": {
      "ndx": 27303.67,
      "spx": 7165.08,
      "ndx_drawdown": -0.04,
      "spx_drawdown": -0.05,
      "ndx_above_ma200": 53.0,
      "spx_above_ma200": 57.0,
      "ndx_deviation_ma200": 10.49,
      "spx_deviation_ma200": 6.85,
      "vix": 18.71,
      "vix_term": 0.88,
      "vix_term_days": 0,
      "credit_spread": 2.86,
      "rate_shock": false,
      "aaii_valid": false,
      "qqq_oi_ratio": 1.51,
      "qqq_oi_deviation": null,
      "spy_oi_ratio": 2.18,
      "spy_oi_deviation": null,
      "on_rrp_deviation": -95.14,
      "ndx_spx_deviation": 3.0,
      "iwm_spy_deviation": 0.55
    },
    "signal": {
      "emotion": "中性",
      "strength": "普通",
      "triggered_conditions": [],
      "target_position": "80%",
      "action": "维持底仓正常定投"
    },
    "verify_5d": {
      "status": "verified",
      "ndx_return": 1.36,
      "spx_return": 1.19,
      "weighted_return": 1.32,
      "result": "correct",
      "divergence": "同步运行"
    },
    "verify_20d": {
      "status": "pending",
      "ndx_return": null,
      "spx_return": null,
      "weighted_return": null,
      "result": null,
      "divergence": null
    }
  },
  {
    "date": "2026-04-27",
    "market_data": {
      "ndx": 27303.67,
      "spx": 7165.08,
      "ndx_drawdown": -0.04,
      "spx_drawdown": -0.05,
      "ndx_above_ma200": 53.0,
      "spx_above_ma200": 57.0,
      "ndx_deviation_ma200": 10.49,
      "spx_deviation_ma200": 6.85,
      "vix": 18.71,
      "vix_term": 0.88,
      "vix_term_days": 0,
      "credit_spread": 2.86,
      "rate_shock": false,
      "aaii_valid": false,
      "qqq_oi_ratio": 1.51,
      "qqq_oi_deviation": null,
      "spy_oi_ratio": 2.18,
      "spy_oi_deviation": null,
      "on_rrp_deviation": -95.14,
      "ndx_spx_deviation": 3.0,
      "iwm_spy_deviation": 0.55
    },
    "signal": {
      "emotion": "中性",
      "strength": "普通",
      "triggered_conditions": [],
      "target_position": "80%",
      "action": "维持底仓正常定投"
    },
    "verify_5d": {
      "status": "verified",
      "ndx_return": 1.03,
      "spx_return": 0.27,
      "weighted_return": 0.84,
      "result": "correct",
      "divergence": "同步运行"
    },
    "verify_20d": {
      "status": "pending",
      "ndx_return": null,
      "spx_return": null,
      "weighted_return": null,
      "result": null,
      "divergence": null
    }
  },
  {
    "date": "2026-04-28",
    "market_data": {
      "ndx": 27305.68,
      "spx": 7173.91,
      "ndx_drawdown": -0.03,
      "spx_drawdown": -0.07,
      "ndx_above_ma200": 53.0,
      "spx_above_ma200": 57.0,
      "ndx_deviation_ma200": 10.4,
      "spx_deviation_ma200": 6.91,
      "vix": 18.02,
      "vix_term": 0.87,
      "vix_term_days": 0,
      "credit_spread": 2.86,
      "rate_shock": false,
      "aaii_valid": false,
      "qqq_oi_ratio": 1.51,
      "qqq_oi_deviation": null,
      "spy_oi_ratio": 2.21,
      "spy_oi_deviation": null,
      "on_rrp_deviation": -77.83,
      "ndx_spx_deviation": 2.64,
      "iwm_spy_deviation": 0.5
    },
    "signal": {
      "emotion": "中性",
      "strength": "普通",
      "triggered_conditions": [],
      "target_position": "80%",
      "action": "维持底仓正常定投"
    },
    "verify_5d": {
      "status": "verified",
      "ndx_return": 3.63,
      "spx_return": 1.68,
      "weighted_return": 3.14,
      "result": "correct",
      "divergence": "同步运行"
    },
    "verify_20d": {
      "status": "pending",
      "ndx_return": null,
      "spx_return": null,
      "weighted_return": null,
      "result": null,
      "divergence": null
    }
  },
  {
    "date": "2026-04-29",
    "market_data": {
      "ndx": 26944.47,
      "spx": 7127.01,
      "ndx_drawdown": -1.36,
      "spx_drawdown": -0.72,
      "ndx_above_ma200": 53.0,
      "spx_above_ma200": 57.0,
      "ndx_deviation_ma200": 8.85,
      "spx_deviation_ma200": 6.15,
      "vix": 18.54,
      "vix_term": 0.88,
      "vix_term_days": 0,
      "credit_spread": 2.86,
      "rate_shock": false,
      "aaii_valid": false,
      "qqq_oi_ratio": 1.53,
      "qqq_oi_deviation": null,
      "spy_oi_ratio": 1.87,
      "spy_oi_deviation": null,
      "on_rrp_deviation": -77.83,
      "ndx_spx_deviation": 1.73,
      "iwm_spy_deviation": -0.21
    },
    "signal": {
      "emotion": "中性",
      "strength": "普通",
      "triggered_conditions": [],
      "target_position": "80%",
      "action": "维持底仓正常定投"
    },
    "verify_5d": {
      "status": "verified",
      "ndx_return": 5.19,
      "spx_return": 3.21,
      "weighted_return": 4.7,
      "result": "correct",
      "divergence": "同步运行"
    },
    "verify_20d": {
      "status": "pending",
      "ndx_return": null,
      "spx_return": null,
      "weighted_return": null,
      "result": null,
      "divergence": null
    }
  },
  {
    "date": "2026-04-30",
    "market_data": {
      "ndx": 27186.98,
      "spx": 7135.95,
      "ndx_drawdown": -0.47,
      "spx_drawdown": -0.6,
      "ndx_above_ma200": 52.47,
      "spx_above_ma200": 53.67,
      "ndx_deviation_ma200": 9.73,
      "spx_deviation_ma200": 6.21,
      "vix": 18.81,
      "vix_term": 0.89,
      "vix_term_days": 0,
      "credit_spread": 2.85,
      "rate_shock": false,
      "aaii_valid": false,
      "qqq_oi_ratio": 1.5,
      "qqq_oi_deviation": -0.7,
      "spy_oi_ratio": 2.21,
      "spy_oi_deviation": 3.8,
      "on_rrp_deviation": -54.69,
      "ndx_spx_deviation": 2.27,
      "iwm_spy_deviation": -0.92
    },
    "signal": {
      "emotion": "中性",
      "strength": "普通",
      "triggered_conditions": [],
      "target_position": "80%",
      "action": "维持底仓正常定投"
    },
    "verify_5d": {
      "status": "verified",
      "ndx_return": 4.05,
      "spx_return": 1.78,
      "weighted_return": 3.48,
      "result": "correct",
      "divergence": "同步运行"
    },
    "verify_20d": {
      "status": "pending",
      "ndx_return": null,
      "spx_return": null,
      "weighted_return": null,
      "result": null,
      "divergence": null
    }
  },
  {
    "date": "2026-05-01",
    "market_data": {
      "ndx": 27452.12,
      "spx": 7209.01,
      "ndx_drawdown": -0.13,
      "spx_drawdown": -0.15,
      "ndx_above_ma200": 56.43,
      "spx_above_ma200": 57.25,
      "ndx_deviation_ma200": 10.7,
      "spx_deviation_ma200": 7.22,
      "vix": 16.89,
      "vix_term": 0.84,
      "vix_term_days": 0,
      "credit_spread": 2.82,
      "rate_shock": false,
      "aaii_valid": false,
      "qqq_oi_ratio": 1.5,
      "qqq_oi_deviation": -0.7,
      "spy_oi_ratio": 2.26,
      "spy_oi_deviation": 5.1,
      "on_rrp_deviation": 359.77,
      "ndx_spx_deviation": 2.01,
      "iwm_spy_deviation": 0.15
    },
    "signal": {
      "emotion": "中性",
      "strength": "普通",
      "triggered_conditions": [],
      "target_position": "80%",
      "action": "维持底仓正常定投"
    },
    "verify_5d": {
      "status": "pending",
      "ndx_return": null,
      "spx_return": null,
      "weighted_return": null,
      "result": null,
      "divergence": null
    },
    "verify_20d": {
      "status": "pending",
      "ndx_return": null,
      "spx_return": null,
      "weighted_return": null,
      "result": null,
      "divergence": null
    }
  },
  {
    "date": "2026-05-04",
    "market_data": {
      "ndx": 28013.35,
      "spx": 7253.97,
      "ndx_drawdown": -0.02,
      "spx_drawdown": -0.26,
      "ndx_above_ma200": 56.43,
      "spx_above_ma200": 55.46,
      "ndx_deviation_ma200": 12.63,
      "spx_deviation_ma200": 7.66,
      "vix": 17.44,
      "vix_term": 0.84,
      "vix_term_days": 0,
      "credit_spread": 2.78,
      "rate_shock": false,
      "aaii_valid": false,
      "qqq_oi_ratio": 1.59,
      "qqq_oi_deviation": 3.9,
      "spy_oi_ratio": 2.28,
      "spy_oi_deviation": 4.6,
      "on_rrp_deviation": -15.7,
      "ndx_spx_deviation": 2.67,
      "iwm_spy_deviation": 0.69
    },
    "signal": {
      "emotion": "中性",
      "strength": "★ 弱",
      "triggered_conditions": [],
      "target_position": "100%",
      "action": "持有"
    },
    "verify_5d": {
      "status": "pending",
      "ndx_return": null,
      "spx_return": null,
      "weighted_return": null,
      "result": null,
      "divergence": null
    },
    "verify_20d": {
      "status": "pending",
      "ndx_return": null,
      "spx_return": null,
      "weighted_return": null,
      "result": null,
      "divergence": null
    }
  },
  {
    "date": "2026-05-05",
    "market_data": {
      "ndx": 27587.84,
      "spx": 7192.6,
      "ndx_drawdown": -0.84,
      "spx_drawdown": -1.1,
      "ndx_above_ma200": 55.44,
      "spx_above_ma200": 55.46,
      "ndx_deviation_ma200": 11.03,
      "spx_deviation_ma200": 6.83,
      "vix": 18.58,
      "vix_term": 0.88,
      "vix_term_days": 0,
      "credit_spread": 2.77,
      "rate_shock": false,
      "aaii_valid": false,
      "qqq_oi_ratio": 1.58,
      "qqq_oi_deviation": 3.9,
      "spy_oi_ratio": 2.27,
      "spy_oi_deviation": 4.6,
      "on_rrp_deviation": -16.65,
      "ndx_spx_deviation": 2.26,
      "iwm_spy_deviation": -0.13
    },
    "signal": {
      "emotion": "中性",
      "strength": "普",
      "triggered_conditions": [],
      "target_position": "维持底仓正常定投",
      "action": "维持底仓正常定投"
    },
    "verify_5d": {
      "status": "pending",
      "ndx_return": null,
      "spx_return": null,
      "weighted_return": null,
      "result": null,
      "divergence": null
    },
    "verify_20d": {
      "status": "pending",
      "ndx_return": null,
      "spx_return": null,
      "weighted_return": null,
      "result": null,
      "divergence": null
    }
  },
  {
    "date": "2026-05-06",
    "market_data": {
      "ndx": 28599.17,
      "spx": 7365.12,
      "ndx_drawdown": -0.03,
      "spx_drawdown": -0.06,
      "ndx_above_ma200": 55.44,
      "spx_above_ma200": 55.86,
      "ndx_deviation_ma200": 14.86,
      "spx_deviation_ma200": 9.23,
      "vix": 17.39,
      "vix_term": 0.85,
      "vix_term_days": 0,
      "credit_spread": 2.77,
      "rate_shock": false,
      "aaii_valid": false,
      "qqq_oi_ratio": 1.64,
      "qqq_oi_deviation": 6.5,
      "spy_oi_ratio": 2.39,
      "spy_oi_deviation": 8.1,
      "on_rrp_deviation": 114.24,
      "ndx_spx_deviation": 2.95,
      "iwm_spy_deviation": 0.93
    },
    "signal": {
      "emotion": "中性",
      "strength": "★ 弱",
      "triggered_conditions": [],
      "target_position": "100%",
      "action": "持有"
    },
    "verify_5d": {
      "status": "pending",
      "ndx_return": null,
      "spx_return": null,
      "weighted_return": null,
      "result": null,
      "divergence": null
    },
    "verify_20d": {
      "status": "pending",
      "ndx_return": null,
      "spx_return": null,
      "weighted_return": null,
      "result": null,
      "divergence": null
    }
  },
  {
    "date": "2026-05-07",
    "market_data": {
      "ndx": 28563.95,
      "spx": 7337.11,
      "ndx_drawdown": -0.91,
      "spx_drawdown": -0.65,
      "ndx_above_ma200": 57.42,
      "spx_above_ma200": 55.26,
      "ndx_deviation_ma200": 14.6,
      "spx_deviation_ma200": 8.73,
      "vix": 17.08,
      "vix_term": 0.84,
      "vix_term_days": 0,
      "credit_spread": 2.75,
      "rate_shock": false,
      "aaii_valid": false,
      "qqq_oi_ratio": 1.63,
      "qqq_oi_deviation": 5.2,
      "spy_oi_ratio": 2.41,
      "spy_oi_deviation": 8.1,
      "on_rrp_deviation": 1.04,
      "ndx_spx_deviation": 2.92,
      "iwm_spy_deviation": -0.37
    },
    "signal": {
      "emotion": "中性",
      "strength": "★ 弱",
      "triggered_conditions": [],
      "target_position": "100%",
      "action": "持有"
    },
    "verify_5d": {
      "status": "pending",
      "ndx_return": null,
      "spx_return": null,
      "weighted_return": null,
      "result": null,
      "divergence": null
    },
    "verify_20d": {
      "status": "pending",
      "ndx_return": null,
      "spx_return": null,
      "weighted_return": null,
      "result": null,
      "divergence": null
    }
  }
]